subtitle_splitter_fr/__init__.py
subtitle_splitter_fr/preprocessing_utils.py
subtitle_splitter_fr/splitter.py
subtitle_splitter_fr/splitting_strategies.py
subtitle_splitter_fr/models/tokenizer/added_tokens.json
subtitle_splitter_fr/models/tokenizer/sentencepiece.bpe.model
subtitle_splitter_fr/models/tokenizer/special_tokens_map.json
subtitle_splitter_fr/models/tokenizer/tokenizer.json
subtitle_splitter_fr/models/tokenizer/tokenizer_config.json
subtitle_splitter_fr-0.1.1.3.dist-info/METADATA
subtitle_splitter_fr-0.1.1.3.dist-info/WHEEL
subtitle_splitter_fr-0.1.1.3.dist-info/top_level.txt
subtitle_splitter_fr-0.1.1.3.dist-info/RECORD
