Metadata-Version: 2.4
Name: subtitle_splitter_fr
Version: 0.1.1.3
Summary: Divise des textes en sous-titres basés sur un modèle ONNX.
Author-email: Jules Goueffon <jules.goueffon89@gmail.com>
License: MIT
Project-URL: Homepage, https://github.com/julesGoueffon/subtitle_splitter_fr
Project-URL: Bug Tracker, https://github.com/julesGoueffon/subtitle_splitter_fr/issues
Classifier: Programming Language :: Python :: 3
Classifier: License :: OSI Approved :: MIT License
Classifier: Operating System :: OS Independent
Classifier: Natural Language :: French
Classifier: Topic :: Text Processing :: Linguistic
Requires-Python: >=3.8
Requires-Dist: nltk
Requires-Dist: numpy
Requires-Dist: onnxruntime
Requires-Dist: transformers
Requires-Dist: importlib-resources
Requires-Dist: huggingface_hub
